soda/__init__.py
soda/core.py
soda/dataflow.py
soda/grammar.py
soda/mutator.py
soda/sodac.py
soda/tensor.py
soda/util.py
soda/visitor.py
soda/codegen/__init__.py
soda/codegen/frt/__init__.py
soda/codegen/frt/core.py
soda/codegen/frt/host.py
soda/codegen/intel/__init__.py
soda/codegen/intel/ocl_kernel.py
soda/codegen/intel/opencl.py
soda/codegen/xilinx/__init__.py
soda/codegen/xilinx/header.py
soda/codegen/xilinx/hls_kernel.py
soda/codegen/xilinx/host.py
soda/codegen/xilinx/opencl.py
soda/codegen/xilinx/rtl_kernel.py
soda/model/__init__.py
soda/model/resource.py
soda/model/xilinx.py
soda/optimization/__init__.py
soda/optimization/args.py
soda/optimization/cluster.py
soda/optimization/computation_reuse.py
soda/optimization/inline.py
sodac-0.0.20220505.dev2.dist-info/METADATA
sodac-0.0.20220505.dev2.dist-info/WHEEL
sodac-0.0.20220505.dev2.dist-info/entry_points.txt
sodac-0.0.20220505.dev2.dist-info/top_level.txt
sodac-0.0.20220505.dev2.dist-info/RECORD
