Metadata-Version: 2.1
Name: sodac
Version: 0.0.20220505.dev2
Summary: Stencil with optimized dataflow architecture
Home-page: https://github.com/Blaok/soda
Author: Blaok Chi
License: UNKNOWN
Platform: UNKNOWN
Classifier: Development Status :: 2 - Pre-Alpha
Classifier: Intended Audience :: Developers
Classifier: Intended Audience :: Science/Research
Classifier: License :: OSI Approved :: MIT License
Classifier: Programming Language :: Python :: 3 :: Only
Classifier: Programming Language :: Python :: 3
Classifier: Programming Language :: Python :: 3.6
Classifier: Programming Language :: Python :: 3.7
Classifier: Programming Language :: Python :: 3.8
Classifier: Programming Language :: Python :: 3.9
Classifier: Topic :: System :: Hardware
Requires-Python: >=3.6
Requires-Dist: absl-py
Requires-Dist: cached-property
Requires-Dist: haoda (>=0.0.20211016.dev1)
Requires-Dist: pulp
Requires-Dist: tapa (>=0.0.20220505.1)
Requires-Dist: textx
Requires-Dist: toposort
